[
  {
    "id": "audio-speed",
    "name": "Audio Speed Changer",
    "category": "audio",
    "description": "Speed up or slow down audio without changing pitch.",
    "icon": "⏩",
    "href": "/tools/audio-speed",
    "status": "done"
  },
  {
    "id": "boost-audio",
    "name": "Volume Booster",
    "category": "audio",
    "description": "Increase or decrease the volume of an audio file.",
    "icon": "🔊",
    "href": "/tools/boost-audio",
    "status": "done"
  },
  {
    "id": "convert-audio",
    "name": "Audio Converter",
    "category": "audio",
    "description": "Convert audio between MP3, WAV, OGG, FLAC, and AAC formats.",
    "icon": "🔄",
    "href": "/tools/convert-audio",
    "status": "done"
  },
  {
    "id": "merge-audio",
    "name": "Audio Merger",
    "category": "audio",
    "description": "Combine multiple audio files into one.",
    "icon": "🔗",
    "href": "/tools/merge-audio",
    "status": "done"
  },
  {
    "id": "normalize-audio",
    "name": "Volume Normalizer",
    "category": "audio",
    "description": "Equalize volume levels across an audio file.",
    "icon": "📊",
    "href": "/tools/normalize-audio",
    "status": "done"
  },
  {
    "id": "reverse-audio",
    "name": "Audio Reverser",
    "category": "audio",
    "description": "Play an audio file backwards.",
    "icon": "⏪",
    "href": "/tools/reverse-audio",
    "status": "done"
  },
  {
    "id": "text-to-speech",
    "name": "Text to Speech",
    "category": "audio",
    "description": "Convert text to spoken audio. Choose voice, rate, and pitch.",
    "icon": "🗣️",
    "href": "/tools/text-to-speech",
    "status": "done"
  },
  {
    "id": "transcribe-audio",
    "name": "Audio Transcription",
    "category": "audio",
    "description": "Transcribe audio to text using AI. Supports 100+ languages.",
    "icon": "📝",
    "href": "/tools/transcribe-audio",
    "status": "done"
  },
  {
    "id": "trim-audio",
    "name": "Audio Trimmer",
    "category": "audio",
    "description": "Cut and trim audio files by setting start and end time.",
    "icon": "✂️",
    "href": "/tools/trim-audio",
    "status": "done"
  },
  {
    "id": "voice-recorder",
    "name": "Voice Recorder",
    "category": "audio",
    "description": "Record audio from your microphone and download as WAV.",
    "icon": "🎤",
    "href": "/tools/voice-recorder",
    "status": "done"
  },
  {
    "id": "break-even",
    "name": "Break-Even Calculator",
    "category": "business",
    "description": "Calculate the break-even point for your business.",
    "icon": "📈",
    "href": "/tools/break-even",
    "status": "done"
  },
  {
    "id": "churn-calculator",
    "name": "Churn Rate Calculator",
    "category": "business",
    "description": "Calculate customer churn rate and retention.",
    "icon": "📉",
    "href": "/tools/churn-calculator",
    "status": "done"
  },
  {
    "id": "discount-calculator",
    "name": "Discount Calculator",
    "category": "business",
    "description": "Calculate savings and final price after discounts.",
    "icon": "💰",
    "href": "/tools/discount-calculator",
    "status": "done"
  },
  {
    "id": "ltv-calculator",
    "name": "LTV Calculator",
    "category": "business",
    "description": "Calculate Customer Lifetime Value (LTV).",
    "icon": "💎",
    "href": "/tools/ltv-calculator",
    "status": "done"
  },
  {
    "id": "pricing-calculator",
    "name": "Pricing Calculator",
    "category": "business",
    "description": "Calculate optimal product pricing based on costs.",
    "icon": "🏷️",
    "href": "/tools/pricing-calculator",
    "status": "done"
  },
  {
    "id": "profit-margin",
    "name": "Profit Margin Calculator",
    "category": "business",
    "description": "Calculate gross and net profit margins.",
    "icon": "💵",
    "href": "/tools/profit-margin",
    "status": "done"
  },
  {
    "id": "revenue-forecast",
    "name": "Revenue Forecaster",
    "category": "business",
    "description": "Project future revenue based on growth rates.",
    "icon": "📊",
    "href": "/tools/revenue-forecast",
    "status": "done"
  },
  {
    "id": "roi-calculator",
    "name": "ROI Calculator",
    "category": "business",
    "description": "Calculate Return on Investment (ROI) for projects.",
    "icon": "💹",
    "href": "/tools/roi-calculator",
    "status": "done"
  },
  {
    "id": "border-radius-generator",
    "name": "Border Radius Generator",
    "category": "css",
    "description": "Visual editor for CSS border-radius with per-corner control.",
    "icon": "⬜",
    "href": "/tools/border-radius-generator",
    "status": "done"
  },
  {
    "id": "box-shadow-generator",
    "name": "Box Shadow Generator",
    "category": "css",
    "description": "Visual editor for CSS box-shadow with live preview.",
    "icon": "🔲",
    "href": "/tools/box-shadow-generator",
    "status": "done"
  },
  {
    "id": "clip-path-generator",
    "name": "CSS Clip-Path Generator",
    "category": "css",
    "description": "Visual polygon editor for CSS clip-path.",
    "icon": "✂️",
    "href": "/tools/clip-path-generator",
    "status": "done"
  },
  {
    "id": "color-palette",
    "name": "Color Palette Generator",
    "category": "css",
    "description": "Generate harmonious color palettes: complementary, analogous, triadic.",
    "icon": "🎨",
    "href": "/tools/color-palette",
    "status": "done"
  },
  {
    "id": "css-grid-generator",
    "name": "CSS Grid Generator",
    "category": "css",
    "description": "Visual builder for CSS Grid layouts with copy-ready code.",
    "icon": "📐",
    "href": "/tools/css-grid-generator",
    "status": "done"
  },
  {
    "id": "flexbox-playground",
    "name": "Flexbox Playground",
    "category": "css",
    "description": "Interactive CSS Flexbox tester with live preview and code output.",
    "icon": "📦",
    "href": "/tools/flexbox-playground",
    "status": "done"
  },
  {
    "id": "font-pairing",
    "name": "Font Pairing Preview",
    "category": "css",
    "description": "Preview Google Fonts pairings for headings and body text.",
    "icon": "🔤",
    "href": "/tools/font-pairing",
    "status": "done"
  },
  {
    "id": "gradient-generator",
    "name": "CSS Gradient Generator",
    "category": "css",
    "description": "Visual editor for linear, radial, and conic CSS gradients.",
    "icon": "🎨",
    "href": "/tools/gradient-generator",
    "status": "done"
  },
  {
    "id": "cron-builder",
    "name": "Cron Expression Builder",
    "category": "dev",
    "description": "Build cron expressions visually. See human-readable description and next runs.",
    "icon": "⏰",
    "href": "/tools/cron-builder",
    "status": "done"
  },
  {
    "id": "htaccess-generator",
    "name": "HTAccess Generator",
    "category": "dev",
    "description": "Generate .htaccess rules for redirects, caching, and security.",
    "icon": "⚙️",
    "href": "/tools/htaccess-generator",
    "status": "done"
  },
  {
    "id": "json-validator",
    "name": "JSON Validator & Formatter",
    "category": "dev",
    "description": "Validate, format, and minify JSON with error line numbers.",
    "icon": "✅",
    "href": "/tools/json-validator",
    "status": "done"
  },
  {
    "id": "lorem-ipsum",
    "name": "Lorem Ipsum Generator",
    "category": "dev",
    "description": "Generate placeholder text by paragraphs, words, or sentences.",
    "icon": "📝",
    "href": "/tools/lorem-ipsum",
    "status": "done"
  },
  {
    "id": "regex-tester",
    "name": "Regex Tester",
    "category": "dev",
    "description": "Test regular expressions with live matching and capture groups.",
    "icon": "🔍",
    "href": "/tools/regex-tester",
    "status": "done"
  },
  {
    "id": "robots-txt-generator",
    "name": "Robots.txt Generator",
    "category": "dev",
    "description": "Generate robots.txt files for SEO with visual rule builder.",
    "icon": "🤖",
    "href": "/tools/robots-txt-generator",
    "status": "done"
  },
  {
    "id": "user-agent-parser",
    "name": "User Agent Parser",
    "category": "dev",
    "description": "Parse browser, OS, and device info from user agent strings.",
    "icon": "🖥️",
    "href": "/tools/user-agent-parser",
    "status": "done"
  },
  {
    "id": "base64-codec",
    "name": "Base64 Codec",
    "category": "encoding",
    "description": "Encode and decode Base64.",
    "icon": "🔤",
    "href": "/tools/base64-codec",
    "status": "done"
  },
  {
    "id": "hash-generator",
    "name": "Hash Generator",
    "category": "encoding",
    "description": "Generate hash from text using MD5, SHA-1, SHA-256.",
    "icon": "#️⃣",
    "href": "/tools/hash-generator",
    "status": "done"
  },
  {
    "id": "html-entity-codec",
    "name": "HTML Entity Encoder",
    "category": "encoding",
    "description": "Encode HTML entities.",
    "icon": "🏷️",
    "href": "/tools/html-entity-codec",
    "status": "done"
  },
  {
    "id": "jwt-decoder",
    "name": "JWT Decoder",
    "category": "encoding",
    "description": "Decode and inspect JWT tokens.",
    "icon": "🎫",
    "href": "/tools/jwt-decoder",
    "status": "done"
  },
  {
    "id": "morse-code",
    "name": "Morse Code",
    "category": "encoding",
    "description": "Morse code translator.",
    "icon": "📡",
    "href": "/tools/morse-code",
    "status": "done"
  },
  {
    "id": "url-codec",
    "name": "URL Encoder",
    "category": "encoding",
    "description": "Encode and decode URL.",
    "icon": "🔗",
    "href": "/tools/url-codec",
    "status": "done"
  },
  {
    "id": "uuid-generator",
    "name": "UUID Generator",
    "category": "encoding",
    "description": "Generate UUIDs v4 randomly.",
    "icon": "🎲",
    "href": "/tools/uuid-generator",
    "status": "done"
  },
  {
    "id": "compound-interest",
    "name": "Compound Interest Calculator",
    "category": "finance",
    "description": "Calculate compound interest with different compounding frequencies.",
    "icon": "💹",
    "href": "/tools/compound-interest",
    "status": "done"
  },
  {
    "id": "crypto-prices",
    "name": "Crypto Price Tracker",
    "category": "finance",
    "description": "Track live prices of top 50 cryptocurrencies.",
    "icon": "₿",
    "href": "/tools/crypto-prices",
    "status": "done"
  },
  {
    "id": "german-salary-calculator",
    "name": "German Net Salary Calculator",
    "category": "finance",
    "description": "Calculate German net salary with tax class, church tax, and social contributions.",
    "icon": "🇩🇪",
    "href": "/tools/german-salary-calculator",
    "status": "done"
  },
  {
    "id": "inflation-calculator",
    "name": "Inflation Calculator",
    "category": "finance",
    "description": "Calculate the value of money adjusted for inflation over time.",
    "icon": "📊",
    "href": "/tools/inflation-calculator",
    "status": "done"
  },
  {
    "id": "loan-calculator",
    "name": "Loan Calculator",
    "category": "finance",
    "description": "Calculate EMI, total interest, and view amortization schedule.",
    "icon": "💰",
    "href": "/tools/loan-calculator",
    "status": "done"
  },
  {
    "id": "mortgage-calculator",
    "name": "Mortgage Calculator",
    "category": "finance",
    "description": "Calculate monthly mortgage payments and total cost.",
    "icon": "🏠",
    "href": "/tools/mortgage-calculator",
    "status": "done"
  },
  {
    "id": "sip-calculator",
    "name": "SIP Calculator",
    "category": "finance",
    "description": "Calculate returns on Systematic Investment Plan (SIP).",
    "icon": "📈",
    "href": "/tools/sip-calculator",
    "status": "done"
  },
  {
    "id": "tax-calculator",
    "name": "Tax Estimator",
    "category": "finance",
    "description": "Estimate income tax based on income and deductions.",
    "icon": "🧾",
    "href": "/tools/tax-calculator",
    "status": "done"
  },
  {
    "id": "tip-calculator",
    "name": "Tip Calculator",
    "category": "finance",
    "description": "Calculate tip amount and split the bill between people.",
    "icon": "💳",
    "href": "/tools/tip-calculator",
    "status": "done"
  },
  {
    "id": "coin-flip",
    "name": "Coin Flip",
    "category": "fun",
    "description": "Flip a coin. Heads or tails?",
    "icon": "🪙",
    "href": "/tools/coin-flip",
    "status": "done"
  },
  {
    "id": "dice-roller",
    "name": "Dice Roller",
    "category": "fun",
    "description": "Roll dice. Choose 1-6 dice with random results.",
    "icon": "🎲",
    "href": "/tools/dice-roller",
    "status": "done"
  },
  {
    "id": "random-picker",
    "name": "Random Picker",
    "category": "fun",
    "description": "Pick random names from a list. Great for giveaways.",
    "icon": "🎯",
    "href": "/tools/random-picker",
    "status": "done"
  },
  {
    "id": "blood-pressure-checker",
    "name": "Blood Pressure Checker",
    "category": "health",
    "description": "Check and categorize blood pressure readings.",
    "icon": "❤️",
    "href": "/tools/blood-pressure-checker",
    "status": "done"
  },
  {
    "id": "bmi-calculator",
    "name": "BMI Calculator",
    "category": "health",
    "description": "Calculate Body Mass Index with health category and visual gauge.",
    "icon": "⚖️",
    "href": "/tools/bmi-calculator",
    "status": "done"
  },
  {
    "id": "body-fat-calculator",
    "name": "Body Fat Calculator",
    "category": "health",
    "description": "Estimate body fat percentage using US Navy method.",
    "icon": "⚖️",
    "href": "/tools/body-fat-calculator",
    "status": "done"
  },
  {
    "id": "calorie-estimator",
    "name": "Calorie Estimator",
    "category": "health",
    "description": "Estimate daily calorie needs based on age, weight, height, and activity level.",
    "icon": "🔥",
    "href": "/tools/calorie-estimator",
    "status": "done"
  },
  {
    "id": "due-date-calculator",
    "name": "Pregnancy Due Date Calculator",
    "category": "health",
    "description": "Estimate due date from last period with weekly milestones.",
    "icon": "👶",
    "href": "/tools/due-date-calculator",
    "status": "done"
  },
  {
    "id": "heart-rate-zones",
    "name": "Heart Rate Zones",
    "category": "health",
    "description": "Calculate target heart rate zones for exercise.",
    "icon": "💓",
    "href": "/tools/heart-rate-zones",
    "status": "done"
  },
  {
    "id": "ideal-weight",
    "name": "Ideal Weight Calculator",
    "category": "health",
    "description": "Calculate ideal weight range based on height and gender.",
    "icon": "🎯",
    "href": "/tools/ideal-weight",
    "status": "done"
  },
  {
    "id": "macros-calculator",
    "name": "Macros Calculator",
    "category": "health",
    "description": "Calculate daily macronutrient requirements.",
    "icon": "🥗",
    "href": "/tools/macros-calculator",
    "status": "done"
  },
  {
    "id": "ovulation-calculator",
    "name": "Ovulation Calculator",
    "category": "health",
    "description": "Predict ovulation and fertile windows.",
    "icon": "📅",
    "href": "/tools/ovulation-calculator",
    "status": "done"
  },
  {
    "id": "sleep-calculator",
    "name": "Sleep Calculator",
    "category": "health",
    "description": "Find the best times to wake up based on sleep cycles.",
    "icon": "😴",
    "href": "/tools/sleep-calculator",
    "status": "done"
  },
  {
    "id": "water-intake-calculator",
    "name": "Water Intake Calculator",
    "category": "health",
    "description": "Calculate daily hydration needs based on weight.",
    "icon": "💧",
    "href": "/tools/water-intake-calculator",
    "status": "done"
  },
  {
    "id": "add-text-image",
    "name": "Add Text to Image",
    "category": "image",
    "description": "Add custom text overlays to images with fonts, colors, and positioning.",
    "icon": "✏️",
    "href": "/tools/add-text-image",
    "status": "done"
  },
  {
    "id": "brightness-contrast",
    "name": "Brightness & Contrast",
    "category": "image",
    "description": "Adjust brightness, contrast, and saturation of images.",
    "icon": "☀️",
    "href": "/tools/brightness-contrast",
    "status": "done"
  },
  {
    "id": "compress-image",
    "name": "Image Compressor",
    "category": "image",
    "description": "Reduce image file size while maintaining quality. Supports JPG, PNG, WebP.",
    "icon": "📦",
    "href": "/tools/compress-image",
    "status": "done"
  },
  {
    "id": "convert-image",
    "name": "Image Format Converter",
    "category": "image",
    "description": "Convert images between JPG, PNG, WebP, and BMP formats.",
    "icon": "🔄",
    "href": "/tools/convert-image",
    "status": "done"
  },
  {
    "id": "crop-image",
    "name": "Image Cropper",
    "category": "image",
    "description": "Crop images with interactive selection. Preset aspect ratios available.",
    "icon": "✂️",
    "href": "/tools/crop-image",
    "status": "done"
  },
  {
    "id": "favicon-generator",
    "name": "Favicon Generator",
    "category": "image",
    "description": "Generate all favicon sizes from a single image (16, 32, 180, 192, 512px).",
    "icon": "🌐",
    "href": "/tools/favicon-generator",
    "status": "done"
  },
  {
    "id": "grayscale-sepia",
    "name": "Grayscale & Sepia Filter",
    "category": "image",
    "description": "Apply grayscale, sepia, or invert filters to images.",
    "icon": "🎨",
    "href": "/tools/grayscale-sepia",
    "status": "done"
  },
  {
    "id": "image-color-picker",
    "name": "Image Color Picker",
    "category": "image",
    "description": "Pick colors directly from any image.",
    "icon": "🎨",
    "href": "/tools/image-color-picker",
    "status": "done"
  },
  {
    "id": "image-colorizer",
    "name": "Image Colorizer",
    "category": "image",
    "description": "Turn black and white photos into colorful images using AI.",
    "icon": "🎨",
    "href": "/tools/image-colorizer",
    "status": "done"
  },
  {
    "id": "merge-images",
    "name": "Image Merger",
    "category": "image",
    "description": "Combine multiple images into one. Horizontal, vertical, or grid layout.",
    "icon": "🖼️",
    "href": "/tools/merge-images",
    "status": "done"
  },
  {
    "id": "remove-background",
    "name": "Background Remover",
    "category": "image",
    "description": "Remove background from images using AI. Works 100% in your browser.",
    "icon": "🎭",
    "href": "/tools/remove-background",
    "status": "done"
  },
  {
    "id": "remove-exif",
    "name": "Remove EXIF Metadata",
    "category": "image",
    "description": "Strip all metadata (GPS, camera info, date) from images for privacy.",
    "icon": "🔒",
    "href": "/tools/remove-exif",
    "status": "done"
  },
  {
    "id": "resize-image",
    "name": "Image Resizer",
    "category": "image",
    "description": "Change image dimensions. Resize by pixels, percentage, or social media presets.",
    "icon": "📐",
    "href": "/tools/resize-image",
    "status": "done"
  },
  {
    "id": "rotate-flip-image",
    "name": "Rotate & Flip Image",
    "category": "image",
    "description": "Rotate images 90°, 180°, 270° or flip horizontally/vertically.",
    "icon": "🔄",
    "href": "/tools/rotate-flip-image",
    "status": "done"
  },
  {
    "id": "split-image",
    "name": "Image Splitter",
    "category": "image",
    "description": "Split any image into a grid of equal-sized tiles. Perfect for Instagram carousel posts, photo grids, or creating puzzle-like image collections.",
    "icon": "✂️",
    "href": "/tools/split-image",
    "status": "done"
  },
  {
    "id": "upscale-image",
    "name": "Image Upscaler",
    "category": "image",
    "description": "Upscale images 2x or 4x using AI super-resolution.",
    "icon": "🔍",
    "href": "/tools/upscale-image",
    "status": "done"
  },
  {
    "id": "view-exif",
    "name": "View EXIF Data",
    "category": "image",
    "description": "View all metadata embedded in an image: camera, lens, ISO, GPS, date.",
    "icon": "ℹ️",
    "href": "/tools/view-exif",
    "status": "done"
  },
  {
    "id": "watermark-image",
    "name": "Add Watermark to Image",
    "category": "image",
    "description": "Add text or logo watermark to images. Adjustable position and opacity.",
    "icon": "💧",
    "href": "/tools/watermark-image",
    "status": "done"
  },
  {
    "id": "age-calculator",
    "name": "Age Calculator",
    "category": "math",
    "description": "Calculate exact age in years, months, days. Next birthday and zodiac sign.",
    "icon": "🎂",
    "href": "/tools/age-calculator",
    "status": "done"
  },
  {
    "id": "base-converter",
    "name": "Number Base Converter",
    "category": "math",
    "description": "Convert between decimal, binary, hexadecimal, and octal.",
    "icon": "🔢",
    "href": "/tools/base-converter",
    "status": "done"
  },
  {
    "id": "date-difference",
    "name": "Date Difference Calculator",
    "category": "math",
    "description": "Calculate the exact difference between two dates in days, weeks, months.",
    "icon": "📅",
    "href": "/tools/date-difference",
    "status": "done"
  },
  {
    "id": "fraction-calculator",
    "name": "Fraction Calculator",
    "category": "math",
    "description": "Add, subtract, multiply, and divide fractions with steps.",
    "icon": "½",
    "href": "/tools/fraction-calculator",
    "status": "done"
  },
  {
    "id": "graph-plotter",
    "name": "Graph Plotter",
    "category": "math",
    "description": "Plot mathematical functions with zoom and pan.",
    "icon": "📈",
    "href": "/tools/graph-plotter",
    "status": "done"
  },
  {
    "id": "percentage-calculator",
    "name": "Percentage Calculator",
    "category": "math",
    "description": "Calculate percentages: what is X% of Y, X is what % of Y, % change.",
    "icon": "%",
    "href": "/tools/percentage-calculator",
    "status": "done"
  },
  {
    "id": "scientific-calculator",
    "name": "Scientific Calculator",
    "category": "math",
    "description": "Full scientific calculator with trig, log, sqrt, and more.",
    "icon": "🔢",
    "href": "/tools/scientific-calculator",
    "status": "done"
  },
  {
    "id": "unit-converter",
    "name": "Unit Converter",
    "category": "math",
    "description": "Convert between 200+ units across 20 categories.",
    "icon": "🔄",
    "href": "/tools/unit-converter",
    "status": "done"
  },
  {
    "id": "image-to-text",
    "name": "Image to Text (OCR)",
    "category": "ocr",
    "description": "Extract text from images using OCR. Supports 100+ languages.",
    "icon": "📝",
    "href": "/tools/image-to-text",
    "status": "done"
  },
  {
    "id": "pdf-to-text",
    "name": "PDF to Text",
    "category": "ocr",
    "description": "Extract all text content from PDF files.",
    "icon": "📋",
    "href": "/tools/pdf-to-text",
    "status": "done"
  },
  {
    "id": "scanned-pdf-searchable",
    "name": "Scanned PDF to Searchable PDF",
    "category": "ocr",
    "description": "OCR scanned PDFs to make them searchable and copyable.",
    "icon": "🔍",
    "href": "/tools/scanned-pdf-searchable",
    "status": "done"
  },
  {
    "id": "screenshot-to-text",
    "name": "Screenshot to Text",
    "category": "ocr",
    "description": "Paste a screenshot or image from clipboard and extract text.",
    "icon": "📋",
    "href": "/tools/screenshot-to-text",
    "status": "done"
  },
  {
    "id": "compress-pdf",
    "name": "Compress PDF",
    "category": "pdf",
    "description": "Reduce PDF file size while maintaining quality.",
    "icon": "📦",
    "href": "/tools/compress-pdf",
    "status": "done"
  },
  {
    "id": "crop-pdf",
    "name": "Crop PDF Pages",
    "category": "pdf",
    "description": "Crop margins from PDF pages.",
    "icon": "✂️",
    "href": "/tools/crop-pdf",
    "status": "done"
  },
  {
    "id": "excel-to-pdf",
    "name": "Excel to PDF",
    "category": "pdf",
    "description": "Convert Excel spreadsheets (.xlsx) to PDF. Preserves tables and formatting.",
    "icon": "📊",
    "href": "/tools/excel-to-pdf",
    "status": "done"
  },
  {
    "id": "extract-text-pdf",
    "name": "Extract Text from PDF",
    "category": "pdf",
    "description": "Extract all text content from a PDF file.",
    "icon": "📋",
    "href": "/tools/extract-text-pdf",
    "status": "done"
  },
  {
    "id": "fill-pdf-forms",
    "name": "Fill PDF Forms",
    "category": "pdf",
    "description": "Fill in interactive PDF form fields and download.",
    "icon": "✍️",
    "href": "/tools/fill-pdf-forms",
    "status": "done"
  },
  {
    "id": "image-to-pdf",
    "name": "Image to PDF",
    "category": "pdf",
    "description": "Convert images into a PDF document.",
    "icon": "📄",
    "href": "/tools/image-to-pdf",
    "status": "done"
  },
  {
    "id": "merge-pdf",
    "name": "Merge PDF",
    "category": "pdf",
    "description": "Combine multiple PDF files into one. Reorder pages before merging.",
    "icon": "📄",
    "href": "/tools/merge-pdf",
    "status": "done"
  },
  {
    "id": "page-numbers-pdf",
    "name": "Add Page Numbers to PDF",
    "category": "pdf",
    "description": "Add page numbers to every page of a PDF.",
    "icon": "🔢",
    "href": "/tools/page-numbers-pdf",
    "status": "done"
  },
  {
    "id": "pdf-esign",
    "name": "PDF eSign",
    "category": "pdf",
    "description": "Draw your signature and stamp it onto PDF pages. Draw, type, or upload signature.",
    "icon": "✍️",
    "href": "/tools/pdf-esign",
    "status": "done"
  },
  {
    "id": "pdf-metadata-viewer",
    "name": "PDF Metadata Viewer",
    "category": "pdf",
    "description": "View and edit PDF metadata: title, author, creator, creation date, keywords.",
    "icon": "ℹ️",
    "href": "/tools/pdf-metadata-viewer",
    "status": "done"
  },
  {
    "id": "pdf-password-info",
    "name": "PDF Password Info",
    "category": "pdf",
    "description": "Check if a PDF is encrypted, view protection level and permissions.",
    "icon": "🔐",
    "href": "/tools/pdf-password-info",
    "status": "done"
  },
  {
    "id": "pdf-preview",
    "name": "PDF Previewer",
    "category": "pdf",
    "description": "Preview PDF pages and thumbnails.",
    "icon": "👁️",
    "href": "/tools/pdf-preview",
    "status": "done"
  },
  {
    "id": "pdf-to-excel",
    "name": "PDF to Excel",
    "category": "pdf",
    "description": "Extract tables from PDF and convert to editable Excel spreadsheets.",
    "icon": "📊",
    "href": "/tools/pdf-to-excel",
    "status": "done"
  },
  {
    "id": "pdf-to-image",
    "name": "PDF to Image",
    "category": "pdf",
    "description": "Convert PDF pages to PNG or JPG images.",
    "icon": "🖼️",
    "href": "/tools/pdf-to-image",
    "status": "done"
  },
  {
    "id": "pdf-to-pptx",
    "name": "PDF to PowerPoint",
    "category": "pdf",
    "description": "Convert PDF pages to PowerPoint slides. Each page becomes a slide.",
    "icon": "📽️",
    "href": "/tools/pdf-to-pptx",
    "status": "done"
  },
  {
    "id": "pdf-to-word",
    "name": "PDF to Word",
    "category": "pdf",
    "description": "Convert PDF files to editable Word documents (.docx). Preserves text and basic formatting.",
    "icon": "📄",
    "href": "/tools/pdf-to-word",
    "status": "done"
  },
  {
    "id": "protect-pdf",
    "name": "Protect PDF",
    "category": "pdf",
    "description": "Add password protection to a PDF file.",
    "icon": "🔒",
    "href": "/tools/protect-pdf",
    "status": "done"
  },
  {
    "id": "reorder-pdf",
    "name": "Reorder PDF Pages",
    "category": "pdf",
    "description": "Drag and drop to reorder pages in a PDF.",
    "icon": "↕️",
    "href": "/tools/reorder-pdf",
    "status": "done"
  },
  {
    "id": "rotate-pdf",
    "name": "Rotate PDF",
    "category": "pdf",
    "description": "Rotate PDF pages 90°, 180°, or 270°.",
    "icon": "🔄",
    "href": "/tools/rotate-pdf",
    "status": "done"
  },
  {
    "id": "split-pdf",
    "name": "Split PDF",
    "category": "pdf",
    "description": "Extract specific pages or split a PDF into multiple files.",
    "icon": "✂️",
    "href": "/tools/split-pdf",
    "status": "done"
  },
  {
    "id": "unlock-pdf",
    "name": "Unlock PDF",
    "category": "pdf",
    "description": "Remove password protection from a PDF (requires password).",
    "icon": "🔓",
    "href": "/tools/unlock-pdf",
    "status": "done"
  },
  {
    "id": "watermark-pdf",
    "name": "Add Watermark to PDF",
    "category": "pdf",
    "description": "Add text watermark to every page of a PDF.",
    "icon": "💧",
    "href": "/tools/watermark-pdf",
    "status": "done"
  },
  {
    "id": "word-to-pdf",
    "name": "Word to PDF",
    "category": "pdf",
    "description": "Convert Word documents (.docx) to PDF files. Preserves formatting and layout.",
    "icon": "📝",
    "href": "/tools/word-to-pdf",
    "status": "done"
  },
  {
    "id": "pdf-to-csv",
    "name": "PDF to CSV",
    "category": "pdf",
    "description": "Extract tabular data from PDF to CSV format.",
    "icon": "📊",
    "href": "/tools/pdf-to-csv",
    "status": "done"
  },
  {
    "id": "pdf-to-epub",
    "name": "PDF to EPUB",
    "category": "pdf",
    "description": "Convert PDF to e-book format for e-readers.",
    "icon": "",
    "href": "/tools/pdf-to-epub",
    "status": "done"
  },
  {
    "id": "delete-pdf-pages",
    "name": "Delete PDF Pages",
    "category": "pdf",
    "description": "Remove specific pages from a PDF with visual selector.",
    "icon": "",
    "href": "/tools/delete-pdf-pages",
    "status": "done"
  },
  {
    "id": "pptx-to-pdf",
    "name": "PowerPoint to PDF",
    "category": "pdf",
    "description": "Convert .pptx presentations to PDF files.",
    "icon": "",
    "href": "/tools/pptx-to-pdf",
    "status": "done"
  },
  {
    "id": "epub-to-pdf",
    "name": "EPUB to PDF",
    "category": "pdf",
    "description": "Convert EPUB e-books to PDF format.",
    "icon": "",
    "href": "/tools/epub-to-pdf",
    "status": "done"
  },
  {
    "id": "remove-watermark-pdf",
    "name": "Remove Watermark from PDF",
    "category": "pdf",
    "description": "Remove overlay watermarks from PDF pages.",
    "icon": "",
    "href": "/tools/remove-watermark-pdf",
    "status": "done"
  },
  {
    "id": "png-to-jpg",
    "name": "PNG to JPG Converter",
    "category": "image",
    "description": "Convert PNG images to JPG with quality control.",
    "icon": "",
    "href": "/tools/png-to-jpg",
    "status": "done"
  },
  {
    "id": "jpg-to-png",
    "name": "JPG to PNG Converter",
    "category": "image",
    "description": "Convert JPG images to lossless PNG format.",
    "icon": "",
    "href": "/tools/jpg-to-png",
    "status": "done"
  },
  {
    "id": "jpg-to-pdf",
    "name": "JPG to PDF Converter",
    "category": "pdf",
    "description": "Convert JPG images to PDF documents.",
    "icon": "",
    "href": "/tools/jpg-to-pdf",
    "status": "done"
  },
  {
    "id": "png-to-pdf",
    "name": "PNG to PDF Converter",
    "category": "pdf",
    "description": "Convert PNG images to PDF documents.",
    "icon": "",
    "href": "/tools/png-to-pdf",
    "status": "done"
  },
  {
    "id": "encrypt-file",
    "name": "File Encryption",
    "category": "privacy",
    "description": "Encrypt or decrypt files with AES-GCM password protection.",
    "icon": "🔐",
    "href": "/tools/encrypt-file",
    "status": "done"
  },
  {
    "id": "hash-file",
    "name": "File Hash Generator",
    "category": "privacy",
    "description": "Generate MD5, SHA-1, SHA-256, SHA-512 checksums for files.",
    "icon": "#️⃣",
    "href": "/tools/hash-file",
    "status": "done"
  },
  {
    "id": "password-checker",
    "name": "Password Strength Checker",
    "category": "privacy",
    "description": "Check how strong your password is with detailed feedback.",
    "icon": "🛡️",
    "href": "/tools/password-checker",
    "status": "done"
  },
  {
    "id": "password-generator",
    "name": "Password Generator",
    "category": "privacy",
    "description": "Generate cryptographically secure passwords. Customize length, uppercase, lowercase, numbers, and symbols.",
    "icon": "🔑",
    "href": "/tools/password-generator",
    "status": "done"
  },
  {
    "id": "remove-metadata",
    "name": "Metadata Remover",
    "category": "privacy",
    "description": "Remove hidden metadata from various file types.",
    "icon": "🔒",
    "href": "/tools/remove-metadata",
    "status": "done"
  },
  {
    "id": "steganography",
    "name": "Steganography",
    "category": "privacy",
    "description": "Hide secret text messages inside images.",
    "icon": "🕵️",
    "href": "/tools/steganography",
    "status": "done"
  },
  {
    "id": "barcode-generator",
    "name": "Barcode Generator",
    "category": "qr",
    "description": "Generate barcodes in Code128, EAN-13, UPC-A formats.",
    "icon": "📊",
    "href": "/tools/barcode-generator",
    "status": "done"
  },
  {
    "id": "barcode-scanner",
    "name": "Barcode Scanner",
    "category": "qr",
    "description": "Scan and decode barcodes from images.",
    "icon": "📷",
    "href": "/tools/barcode-scanner",
    "status": "done"
  },
  {
    "id": "qr-generator",
    "name": "QR Code Generator",
    "category": "qr",
    "description": "Generate QR codes from text, URLs, vCard, or WiFi credentials.",
    "icon": "📱",
    "href": "/tools/qr-generator",
    "status": "done"
  },
  {
    "id": "qr-scanner",
    "name": "QR Code Scanner",
    "category": "qr",
    "description": "Scan and decode QR codes from images.",
    "icon": "📷",
    "href": "/tools/qr-scanner",
    "status": "done"
  },
  {
    "id": "book-lookup",
    "name": "Book Info Lookup",
    "category": "reference",
    "description": "Search for book information by ISBN, title, or author.",
    "icon": "📚",
    "href": "/tools/book-lookup",
    "status": "done"
  },
  {
    "id": "dictionary",
    "name": "Dictionary",
    "category": "reference",
    "description": "Look up word definitions, phonetics, examples, and audio pronunciation.",
    "icon": "📖",
    "href": "/tools/dictionary",
    "status": "done"
  },
  {
    "id": "holiday-calendar",
    "name": "Public Holiday Calendar",
    "category": "reference",
    "description": "View public holidays for any country and year.",
    "icon": "📅",
    "href": "/tools/holiday-calendar",
    "status": "done"
  },
  {
    "id": "thesaurus",
    "name": "Thesaurus",
    "category": "reference",
    "description": "Find synonyms, antonyms, and related words.",
    "icon": "📖",
    "href": "/tools/thesaurus",
    "status": "done"
  },
  {
    "id": "keyword-density",
    "name": "Keyword Density Checker",
    "category": "seo",
    "description": "Analyze keyword frequency in your content.",
    "icon": "📊",
    "href": "/tools/keyword-density",
    "status": "done"
  },
  {
    "id": "meta-tag-generator",
    "name": "Meta Tag Generator",
    "category": "seo",
    "description": "Generate SEO meta tags for your website.",
    "icon": "🏷️",
    "href": "/tools/meta-tag-generator",
    "status": "done"
  },
  {
    "id": "og-generator",
    "name": "Open Graph Generator",
    "category": "seo",
    "description": "Generate Open Graph tags for social media sharing.",
    "icon": "🔗",
    "href": "/tools/og-generator",
    "status": "done"
  },
  {
    "id": "sitemap-generator",
    "name": "Sitemap Generator",
    "category": "seo",
    "description": "Generate XML sitemaps for search engines.",
    "icon": "🗺️",
    "href": "/tools/sitemap-generator",
    "status": "done"
  },
  {
    "id": "slug-generator",
    "name": "URL Slug Generator",
    "category": "seo",
    "description": "Convert titles into search-friendly URL slugs.",
    "icon": "🔗",
    "href": "/tools/slug-generator",
    "status": "done"
  },
  {
    "id": "structured-data-generator",
    "name": "Structured Data Generator",
    "category": "seo",
    "description": "Generate JSON-LD structured data for SEO.",
    "icon": "📄",
    "href": "/tools/structured-data-generator",
    "status": "done"
  },
  {
    "id": "case-converter",
    "name": "Case Converter",
    "category": "text",
    "description": "Convert text to different cases.",
    "icon": "Aa",
    "href": "/tools/case-converter",
    "status": "done"
  },
  {
    "id": "csv-to-excel",
    "name": "CSV to Excel Converter",
    "category": "text",
    "description": "Convert CSV files to Excel format with proper formatting.",
    "icon": "🔄",
    "href": "/tools/csv-to-excel",
    "status": "done"
  },
  {
    "id": "emoji-picker",
    "name": "Emoji Picker",
    "category": "text",
    "description": "Browse and copy emojis. Search by name or browse by category.",
    "icon": "😊",
    "href": "/tools/emoji-picker",
    "status": "done"
  },
  {
    "id": "excel-viewer",
    "name": "Excel Viewer & Editor",
    "category": "text",
    "description": "View and edit Excel spreadsheets (.xlsx, .xls, .csv) in the browser. Export as CSV or new XLSX.",
    "icon": "📊",
    "href": "/tools/excel-viewer",
    "status": "done"
  },
  {
    "id": "json-csv",
    "name": "JSON to CSV",
    "category": "text",
    "description": "Convert JSON array to CSV format.",
    "icon": "📊",
    "href": "/tools/json-csv",
    "status": "done"
  },
  {
    "id": "latex-renderer",
    "name": "LaTeX Renderer",
    "category": "text",
    "description": "Render LaTeX equations to images. Preview and export as PNG.",
    "icon": "∑",
    "href": "/tools/latex-renderer",
    "status": "done"
  },
  {
    "id": "markdown-html",
    "name": "Markdown to HTML",
    "category": "text",
    "description": "Convert Markdown to HTML with live preview.",
    "icon": "📄",
    "href": "/tools/markdown-html",
    "status": "done"
  },
  {
    "id": "readability-score",
    "name": "Readability Score",
    "category": "text",
    "description": "Check text readability with Flesch-Kincaid grade level and reading ease.",
    "icon": "📊",
    "href": "/tools/readability-score",
    "status": "done"
  },
  {
    "id": "text-cleaner",
    "name": "Text Cleaner",
    "category": "text",
    "description": "Clean and normalize text.",
    "icon": "🧹",
    "href": "/tools/text-cleaner",
    "status": "done"
  },
  {
    "id": "text-diff",
    "name": "Text Diff",
    "category": "text",
    "description": "Compare two texts and see the differences.",
    "icon": "🔀",
    "href": "/tools/text-diff",
    "status": "done"
  },
  {
    "id": "text-similarity",
    "name": "Text Similarity",
    "category": "text",
    "description": "Compare text similarity.",
    "icon": "🔗",
    "href": "/tools/text-similarity",
    "status": "done"
  },
  {
    "id": "text-summarizer",
    "name": "Text Summarizer",
    "category": "text",
    "description": "Summarize long text using extractive method.",
    "icon": "📝",
    "href": "/tools/text-summarizer",
    "status": "done"
  },
  {
    "id": "text-to-handwriting",
    "name": "Text to Handwriting",
    "category": "text",
    "description": "Convert text to handwritten-style images. Choose from different handwriting fonts.",
    "icon": "✍",
    "href": "/tools/text-to-handwriting",
    "status": "done"
  },
  {
    "id": "unicode-explorer",
    "name": "Unicode Explorer",
    "category": "text",
    "description": "Explore Unicode characters. Search by name, code point, or browse categories.",
    "icon": "🔤",
    "href": "/tools/unicode-explorer",
    "status": "done"
  },
  {
    "id": "word-counter",
    "name": "Word Counter",
    "category": "text",
    "description": "Count words, characters, sentences, and paragraphs.",
    "icon": "🔢",
    "href": "/tools/word-counter",
    "status": "done"
  },
  {
    "id": "word-frequency",
    "name": "Word Frequency",
    "category": "text",
    "description": "Analyze word frequency in text.",
    "icon": "📈",
    "href": "/tools/word-frequency",
    "status": "done"
  },
  {
    "id": "xml-json",
    "name": "XML to JSON",
    "category": "text",
    "description": "Convert XML to JSON format.",
    "icon": "📋",
    "href": "/tools/xml-json",
    "status": "done"
  },
  {
    "id": "xml-to-csv",
    "name": "XML to CSV Converter",
    "category": "text",
    "description": "Convert XML files to CSV format. Extract data tables from XML documents.",
    "icon": "📊",
    "href": "/tools/xml-to-csv",
    "status": "done"
  },
  {
    "id": "yaml-json",
    "name": "YAML to JSON",
    "category": "text",
    "description": "Convert YAML to JSON format.",
    "icon": "🔄",
    "href": "/tools/yaml-json",
    "status": "done"
  },
  {
    "id": "timestamp-converter",
    "name": "Timestamp Converter",
    "category": "encoding",
    "description": "Convert between Unix timestamps and human-readable dates.",
    "icon": "⏰",
    "href": "/tools/timestamp-converter",
    "status": "done"
  },
  {
    "id": "add-audio-video",
    "name": "Add Audio to Video",
    "category": "video",
    "description": "Merge audio track onto a video file.",
    "icon": "🔊",
    "href": "/tools/add-audio-video",
    "status": "done"
  },
  {
    "id": "compress-video",
    "name": "Video Compressor",
    "category": "video",
    "description": "Reduce video file size by adjusting quality, resolution, and bitrate.",
    "icon": "📦",
    "href": "/tools/compress-video",
    "status": "done"
  },
  {
    "id": "convert-video",
    "name": "Video Format Converter",
    "category": "video",
    "description": "Convert videos between MP4, WebM, AVI, and MOV formats.",
    "icon": "🔄",
    "href": "/tools/convert-video",
    "status": "done"
  },
  {
    "id": "images-to-video",
    "name": "Images to Video",
    "category": "video",
    "description": "Create a video from a sequence of images with custom FPS.",
    "icon": "🎬",
    "href": "/tools/images-to-video",
    "status": "done"
  },
  {
    "id": "mute-video",
    "name": "Mute Video",
    "category": "video",
    "description": "Remove audio track from a video file.",
    "icon": "🔇",
    "href": "/tools/mute-video",
    "status": "done"
  },
  {
    "id": "trim-video",
    "name": "Video Trimmer",
    "category": "video",
    "description": "Cut and trim videos by setting start and end time.",
    "icon": "✂️",
    "href": "/tools/trim-video",
    "status": "done"
  },
  {
    "id": "video-speed",
    "name": "Video Speed Changer",
    "category": "video",
    "description": "Speed up or slow down videos. 0.25x to 4x speed.",
    "icon": "⏩",
    "href": "/tools/video-speed",
    "status": "done"
  },
  {
    "id": "video-to-audio",
    "name": "Video to Audio",
    "category": "video",
    "description": "Extract audio track from video files. Save as MP3 or WAV.",
    "icon": "🎵",
    "href": "/tools/video-to-audio",
    "status": "done"
  },
  {
    "id": "video-to-gif",
    "name": "Video to GIF",
    "category": "video",
    "description": "Convert video clips to animated GIF images.",
    "icon": "🎞️",
    "href": "/tools/video-to-gif",
    "status": "done"
  },
  {
    "id": "video-to-images",
    "name": "Video to Images",
    "category": "video",
    "description": "Extract frames from a video as PNG or JPG images.",
    "icon": "🖼️",
    "href": "/tools/video-to-images",
    "status": "done"
  },
  {
    "id": "chart-generator",
    "name": "Chart Generator",
    "category": "visualization",
    "description": "Create bar, line, pie, doughnut, and radar charts from data.",
    "icon": "📊",
    "href": "/tools/chart-generator",
    "status": "done"
  },
  {
    "id": "csv-visualizer",
    "name": "CSV Visualizer",
    "category": "visualization",
    "description": "Upload a CSV file and instantly generate charts.",
    "icon": "📈",
    "href": "/tools/csv-visualizer",
    "status": "done"
  },
  {
    "id": "json-viewer",
    "name": "JSON Viewer",
    "category": "visualization",
    "description": "View JSON data as a collapsible tree with syntax highlighting.",
    "icon": "🌳",
    "href": "/tools/json-viewer",
    "status": "done"
  },
  {
    "id": "table-generator",
    "name": "Table Generator",
    "category": "visualization",
    "description": "Create styled tables and export as image, PDF, or CSV.",
    "icon": "📋",
    "href": "/tools/table-generator",
    "status": "done"
  },
  {
    "id": "air-quality",
    "name": "Air Quality Index",
    "category": "weather",
    "description": "Check air quality index and pollutant levels for any location.",
    "icon": "🌬️",
    "href": "/tools/air-quality",
    "status": "done"
  },
  {
    "id": "my-ip",
    "name": "My IP Address",
    "category": "weather",
    "description": "Show your public IP address, location, ISP, and timezone.",
    "icon": "🌐",
    "href": "/tools/my-ip",
    "status": "done"
  },
  {
    "id": "sunrise-sunset",
    "name": "Sunrise & Sunset Times",
    "category": "weather",
    "description": "Calculate sunrise, sunset, golden hour, and day length for any location.",
    "icon": "🌅",
    "href": "/tools/sunrise-sunset",
    "status": "done"
  },
  {
    "id": "weather-forecast",
    "name": "Weather Forecast",
    "category": "weather",
    "description": "Get current weather and 7-day forecast for any city.",
    "icon": "🌤️",
    "href": "/tools/weather-forecast",
    "status": "done"
  },
  {
    "id": "heic-to-jpg",
    "name": "HEIC to JPG Converter",
    "category": "image",
    "description": "Convert iPhone HEIC photos to JPG format.",
    "icon": "",
    "href": "/tools/heic-to-jpg",
    "status": "done"
  },
  {
    "id": "webp-to-jpg",
    "name": "WebP to JPG Converter",
    "category": "image",
    "description": "Convert WebP images to JPG with quality control.",
    "icon": "",
    "href": "/tools/webp-to-jpg",
    "status": "done"
  },
  {
    "id": "jpg-to-webp",
    "name": "JPG to WebP Converter",
    "category": "image",
    "description": "Convert JPG images to WebP with quality control.",
    "icon": "",
    "href": "/tools/jpg-to-webp",
    "status": "done"
  },
  {
    "id": "png-to-svg",
    "name": "PNG to SVG Converter",
    "category": "image",
    "description": "Convert PNG images to SVG vector format.",
    "icon": "",
    "href": "/tools/png-to-svg",
    "status": "done"
  },
  {
    "id": "svg-to-png",
    "name": "SVG to PNG Converter",
    "category": "image",
    "description": "Convert SVG images to PNG with size and background control.",
    "icon": "",
    "href": "/tools/svg-to-png",
    "status": "done"
  },
  {
    "id": "collage-maker",
    "name": "Collage Maker",
    "category": "image",
    "description": "Create beautiful photo collages with customizable layouts, spacing, borders, and backgrounds.",
    "icon": "",
    "href": "/tools/collage-maker",
    "status": "done"
  },
  {
    "id": "color-blindness",
    "name": "Color Blindness Simulator",
    "category": "image",
    "description": "Upload an image and apply color blindness simulations: deuteranopia, protanopia, tritanopia, and more.",
    "icon": "👁️",
    "href": "/tools/color-blindness",
    "status": "done"
  },
  {
    "id": "blur-background",
    "name": "Blur Background",
    "category": "image",
    "description": "Apply blur effects to images. Full blur, radial (depth of field), or linear (tilt-shift) modes.",
    "icon": "",
    "href": "/tools/blur-background",
    "status": "done"
  },
  {
    "id": "add-border-image",
    "name": "Add Border to Image",
    "category": "image",
    "description": "Add customizable borders to images. Solid, dashed, double, or rounded corners with shadow effects.",
    "icon": "",
    "href": "/tools/add-border-image",
    "status": "done"
  },
  {
    "id": "round-image-cropper",
    "name": "Round Image Cropper",
    "category": "image",
    "description": "Crop images into perfect circles with customizable border, shadow, and background options.",
    "icon": "",
    "href": "/tools/round-image-cropper",
    "status": "done"
  },
  {
    "id": "pixelate-image",
    "name": "Pixelate Image",
    "category": "image",
    "description": "Apply pixelation/mosaic effect to images. Adjust pixel size, select regions, and control intensity.",
    "icon": "",
    "href": "/tools/pixelate-image",
    "status": "done"
  },
  {
    "id": "image-sharpening",
    "name": "Image Sharpening",
    "category": "image",
    "description": "Sharpen blurry or soft images using convolution filters. Adjust intensity and preview results in real-time.",
    "icon": "",
    "href": "/tools/image-sharpening",
    "status": "done"
  },
  {
    "id": "remove-text-image",
    "name": "Remove Text from Image",
    "category": "image",
    "description": "Remove unwanted text from images by selecting the area. Uses content-aware fill to blend the background.",
    "icon": "",
    "href": "/tools/remove-text-image",
    "status": "done"
  },
  {
    "id": "gif-to-mp4",
    "name": "GIF to MP4",
    "category": "video",
    "description": "Convert animated GIF to MP4 video. MP4 files are smaller and play on all devices.",
    "icon": "🎬",
    "href": "/tools/gif-to-mp4",
    "status": "done"
  },
  {
    "id": "webm-to-mp4",
    "name": "WEBM to MP4",
    "category": "video",
    "description": "Convert WEBM videos to MP4 format for universal compatibility.",
    "icon": "🔄",
    "href": "/tools/webm-to-mp4",
    "status": "done"
  },
  {
    "id": "mov-to-mp4",
    "name": "MOV to MP4",
    "category": "video",
    "description": "Convert MOV videos from iPhones and cameras to MP4.",
    "icon": "📱",
    "href": "/tools/mov-to-mp4",
    "status": "done"
  },
  {
    "id": "add-subtitles",
    "name": "Add Subtitles to Video",
    "category": "video",
    "description": "Burn SRT or VTT subtitle files permanently into video.",
    "icon": "💬",
    "href": "/tools/add-subtitles",
    "status": "done"
  },
  {
    "id": "video-resizer",
    "name": "Video Resizer",
    "category": "video",
    "description": "Change video resolution to any size with presets or custom dimensions.",
    "icon": "📐",
    "href": "/tools/video-resizer",
    "status": "done"
  },
  {
    "id": "excel-to-xml",
    "name": "Excel to XML",
    "category": "text",
    "description": "Convert Excel spreadsheets (.xlsx) to XML format.",
    "icon": "📊",
    "href": "/tools/excel-to-xml",
    "status": "done"
  },
  {
    "id": "xml-to-excel",
    "name": "XML to Excel",
    "category": "text",
    "description": "Convert XML files to Excel spreadsheets (.xlsx).",
    "icon": "📊",
    "href": "/tools/xml-to-excel",
    "status": "done"
  },
  {
    "id": "csv-splitter",
    "name": "CSV Splitter",
    "category": "text",
    "description": "Split large CSV files into smaller files by row count.",
    "icon": "✂️",
    "href": "/tools/csv-splitter",
    "status": "done"
  },
  {
    "id": "countdown-timer",
    "name": "Countdown Timer",
    "category": "productivity",
    "description": "Count down to a specific date or event with live updates.",
    "icon": "⏳",
    "href": "/tools/countdown-timer",
    "status": "done"
  },
  {
    "id": "drawing-pad",
    "name": "Drawing Pad",
    "category": "productivity",
    "description": "Freehand drawing canvas with export options.",
    "icon": "✏️",
    "href": "/tools/drawing-pad",
    "status": "done"
  },
  {
    "id": "ascii-art",
    "name": "ASCII Art Generator",
    "category": "text",
    "description": "Convert text to figlet-style ASCII art with 50+ font styles.",
    "icon": "🎨",
    "href": "/tools/ascii-art",
    "status": "done"
  },
  {
    "id": "typing-speed-test",
    "name": "Typing Speed Test",
    "category": "fun",
    "description": "Test your typing speed in words per minute with accuracy tracking.",
    "icon": "⌨️",
    "href": "/tools/typing-speed-test",
    "status": "done"
  },
  {
    "id": "stopwatch",
    "name": "Stopwatch with Lap Timer",
    "category": "productivity",
    "description": "Start, pause, and reset a stopwatch with lap time tracking.",
    "icon": "⏱️",
    "href": "/tools/stopwatch",
    "status": "done"
  },
  {
    "id": "number-to-words",
    "name": "Number to Words",
    "category": "text",
    "description": "Convert numerals to written English words.",
    "icon": "🔢",
    "href": "/tools/number-to-words",
    "status": "done"
  },
  {
    "id": "text-to-table",
    "name": "Text to Table Converter",
    "category": "text",
    "description": "Parse CSV/TSV/pipe-delimited text into HTML or Markdown tables.",
    "icon": "📋",
    "href": "/tools/text-to-table",
    "status": "done"
  },
  {
    "id": "subnet-calculator",
    "name": "IP Subnet Calculator",
    "category": "dev",
    "description": "Calculate subnet, network, broadcast, and host ranges.",
    "icon": "🌐",
    "href": "/tools/subnet-calculator",
    "status": "done"
  },
  {
    "id": "css-animation-generator",
    "name": "CSS Animation Generator",
    "category": "css",
    "description": "Visual builder for CSS @keyframes animations.",
    "icon": "🎬",
    "href": "/tools/css-animation-generator",
    "status": "done"
  },
  {
    "id": "color-converter",
    "name": "Color Format Converter",
    "category": "css",
    "description": "Convert between HEX, RGB, HSL, HSV, and CMYK color formats.",
    "icon": "🎨",
    "href": "/tools/color-converter",
    "status": "done"
  },
  {
    "id": "image-filters",
    "name": "Image Filter Gallery",
    "category": "image",
    "description": "Apply cinematic filters to your photos. Click any filter to preview and download.",
    "icon": "🎞️",
    "href": "/tools/image-filters",
    "status": "done"
  },
  {
    "id": "curl-builder",
    "name": "cURL Command Builder",
    "category": "dev",
    "description": "Build cURL commands visually. Select method, add headers, set body, and copy the generated command.",
    "icon": "🔗",
    "href": "/tools/curl-builder",
    "status": "done"
  },
  {
    "id": "duration-calculator",
    "name": "Time Duration Calculator",
    "category": "math",
    "description": "Calculate the exact duration between two dates/times. See results in years, months, weeks, days, hours, minutes, and seconds.",
    "icon": "⏳",
    "href": "/tools/duration-calculator",
    "status": "done"
  },
  {
    "id": "aspect-ratio",
    "name": "Aspect Ratio Calculator",
    "category": "math",
    "description": "Calculate aspect ratios from dimensions, find missing dimensions given a ratio, and see common presets.",
    "icon": "🖼️",
    "href": "/tools/aspect-ratio",
    "status": "done"
  },
  {
    "id": "roman-numerals",
    "name": "Roman Numeral Converter",
    "category": "text",
    "description": "Convert between Roman numerals and Arabic numbers. Supports 1–3999 (I–MMMCMXCIX).",
    "icon": "Ⅿ",
    "href": "/tools/roman-numerals",
    "status": "done"
  },
  {
    "id": "line-sorter",
    "name": "Text Line Sorter",
    "category": "text",
    "description": "Sort, reverse, shuffle, deduplicate, or trim lines of text in one click.",
    "icon": "↕️",
    "href": "/tools/line-sorter",
    "status": "done"
  },
  {
    "id": "palindrome",
    "name": "Palindrome Checker",
    "category": "fun",
    "description": "Check if any word, phrase, or number is a palindrome. See the reversed version and a character comparison.",
    "icon": "🔄",
    "href": "/tools/palindrome",
    "status": "done"
  },
  {
    "id": "url-parser",
    "name": "URL Parser & Builder",
    "category": "dev",
    "description": "Parse any URL into its components or build a URL from parts. View query parameters as a table.",
    "icon": "🔍",
    "href": "/tools/url-parser",
    "status": "done"
  },
  {
    "id": "pdf-secure-redact",
    "name": "PDF Visual Redactor",
    "category": "pdf",
    "description": "Cover sensitive text in PDF pages with black rectangles. Visual redaction only — text is hidden but not permanently removed.",
    "icon": "🔒",
    "href": "/tools/pdf-secure-redact",
    "status": "done"
  },
  {
    "id": "textbook-splitter",
    "name": "Page Textbook Splitter",
    "category": "pdf",
    "description": "Split landscape-scanned book pages down the middle into consecutive portrait pages.",
    "icon": "📖",
    "href": "/tools/textbook-splitter",
    "status": "done"
  },
  {
    "id": "glassmorphism-generator",
    "name": "CSS Glassmorphism Studio",
    "category": "css",
    "description": "Interactive studio for generating cross-browser glassmorphism (frosted glass) CSS with Safari fallbacks.",
    "icon": "🔮",
    "href": "/tools/glassmorphism-generator",
    "status": "done"
  },
  {
    "id": "css-clamp-generator",
    "name": "Fluid Typography (CSS Clamp) Calculator",
    "category": "css",
    "description": "Calculate responsive font scales using CSS clamp() function with preferred viewport mathematical scale.",
    "icon": "📐",
    "href": "/tools/css-clamp-generator",
    "status": "done"
  },
  {
    "id": "svg-blob-generator",
    "name": "Organic SVG Blob & Wave Generator",
    "category": "css",
    "description": "Generate mathematical cubic bezier organic shapes and wave page dividers with zero tracking.",
    "icon": "🌊",
    "href": "/tools/svg-blob-generator",
    "status": "done"
  },
  {
    "id": "css-triangle-generator",
    "name": "CSS Pure Triangle Code Generator",
    "category": "css",
    "description": "Visually construct minimal pure border-based CSS triangles in any direction.",
    "icon": "🔺",
    "href": "/tools/css-triangle-generator",
    "status": "done"
  },
  {
    "id": "sitemap-visualizer",
    "name": "Sitemap XML Visualizer",
    "category": "dev",
    "description": "Parse and display sitemap.xml files as interactive, collapsible directory tree mind-maps.",
    "icon": "🌳",
    "href": "/tools/sitemap-visualizer",
    "status": "done"
  },
  {
    "id": "log-anonymizer",
    "name": "Log File Sensitive Data Masker",
    "category": "dev",
    "description": "Anonymize sensitive data (IPs, emails, tokens, keys) in server logs using secure client-side regex.",
    "icon": "🕵️",
    "href": "/tools/log-anonymizer",
    "status": "done"
  },
  {
    "id": "web-asset-extractor",
    "name": "Website Asset Extractor",
    "category": "dev",
    "description": "Extract SVG nodes, image links, stylesheets, and custom web fonts from pasted raw HTML code.",
    "icon": "📦",
    "href": "/tools/web-asset-extractor",
    "status": "done"
  },
  {
    "id": "security-headers-generator",
    "name": "Security Headers Generator",
    "category": "dev",
    "description": "Configure Content Security Policy (CSP), HSTS, and generate config rules for Nginx, Apache, or Cloudflare.",
    "icon": "🛡️",
    "href": "/tools/security-headers-generator",
    "keywords": ["security", "headers", "csp", "hsts", "content security policy", "nginx", "apache", "cloudflare", "x-frame-options", "referrer-policy"],
    "status": "done"
  },
  {
    "id": "bulk-utm-builder",
    "name": "Bulk UTM Campaign URL Builder",
    "category": "seo",
    "description": "Generate campaign tracking URLs in bulk, manage presets, and export directly to CSV.",
    "icon": "🔗",
    "href": "/tools/bulk-utm-builder",
    "keywords": ["utm", "campaign", "tracking", "url", "bulk", "analytics", "marketing"],
    "status": "done"
  },
  {
    "id": "ambient-sound-mixer",
    "name": "Ambient Focus Soundboard",
    "category": "productivity",
    "description": "Create customizable ambient focus soundtracks using 8 high-quality offline loopable sound nodes.",
    "icon": "🎧",
    "href": "/tools/ambient-sound-mixer",
    "keywords": ["ambient", "sound", "noise", "focus", "sleep", "relax", "rain", "cafe"],
    "status": "done"
  },
  {
    "id": "neumorphism-generator",
    "name": "CSS Neumorphism Studio",
    "category": "css",
    "description": "Interactive tool to generate convex, concave, or pressed neumorphic shadow sets based on hue luminance offset.",
    "icon": "🔘",
    "href": "/tools/neumorphism-generator",
    "keywords": ["neumorphism", "neumorphic", "soft ui", "css shadows", "convex", "concave", "pressed", "extruded"],
    "status": "done"
  },
  {
    "id": "hosts-file-generator",
    "name": "Hosts File Configurator",
    "category": "dev",
    "description": "Generate formatted local network alias hosts configurations from a simple visual key table.",
    "icon": "🌐",
    "href": "/tools/hosts-file-generator",
    "keywords": ["hosts", "hosts file", "local network", "dns", "aliases", "network configuration", "etc hosts"],
    "status": "done"
  },
  {
    "id": "subtitle-time-shifter",
    "name": "SRT / VTT Subtitle Sync Shifter",
    "category": "productivity",
    "description": "Adjust SRT and VTT subtitle timestamps client-side with millisecond accuracy sync offsets.",
    "icon": "⏱️",
    "href": "/tools/subtitle-time-shifter",
    "keywords": ["subtitle", "srt", "vtt", "sync", "timestamp", "shift", "adjust", "subtitles"],
    "status": "done"
  },
  {
    "id": "xml-formatter",
    "name": "XML Formatter & Validator",
    "category": "text",
    "description": "Format, validate, and highlight XML markup without server transmissions.",
    "icon": "📝",
    "href": "/tools/xml-formatter",
    "keywords": ["xml", "formatter", "validator", "beautifier", "pretty print", "xml validator", "xml formatter"],
    "status": "done"
  },
  {
    "id": "sql-to-json",
    "name": "SQL to JSON & Schema Converter",
    "category": "dev",
    "description": "Parse SQL CREATE TABLE and INSERT INTO queries to generate structured JSON schemas and arrays.",
    "icon": "🗃️",
    "href": "/tools/sql-to-json",
    "keywords": ["sql", "json", "schema", "converter", "database", "parser"],
    "status": "done"
  },
  {
    "id": "git-changelog-generator",
    "name": "Conventional Commit Changelog Generator",
    "category": "text",
    "description": "Parse conventional git logs and compile beautiful categorized Markdown release changelogs.",
    "icon": "📜",
    "href": "/tools/git-changelog-generator",
    "keywords": ["git", "changelog", "commit", "release", "conventional", "markdown"],
    "status": "done"
  }
]
